tqdm_logger.py
tqdm_logger-1.0.1.data/scripts/tqdm_logger.py
tqdm_logger-1.0.1.dist-info/LICENSE
tqdm_logger-1.0.1.dist-info/METADATA
tqdm_logger-1.0.1.dist-info/WHEEL
tqdm_logger-1.0.1.dist-info/top_level.txt
tqdm_logger-1.0.1.dist-info/RECORD
