Metadata-Version: 2.1
Name: tqdm-logger
Version: 1.0.1
Summary: TQDM Logging utility
Home-page: https://github.com/adarsh-anand15/tqdm_logger
Author: Adarsh Anand
License: GNU General Public License v3.0
Platform: UNKNOWN
Requires-Dist: tqdm
